ratehttp/__init__.py
ratehttp/ratehttp.py
ratehttp-0.1.3.dist-info/LICENSE
ratehttp-0.1.3.dist-info/METADATA
ratehttp-0.1.3.dist-info/WHEEL
ratehttp-0.1.3.dist-info/top_level.txt
ratehttp-0.1.3.dist-info/RECORD
