Metadata-Version: 2.1
Name: ratehttp
Version: 0.1.3
Summary: ratehttp is fork from octopus-api based on aiohttp, and ratehttp provides ssl-verify setting
Home-page: https://github.com/dreambe/ratehttp
Author: Shark
Author-email: shark.wangl@gmail.com
Classifier: Programming Language :: Python :: 3
Classifier: License :: OSI Approved :: MIT License
Classifier: Operating System :: OS Independent
Requires-Python: >=3.7
License-File: LICENSE
